amirliber/__init__.py
amirliber/amir.py
yourlibname-0.1.0.dist-info/licenses/LICENSE
yourlibname-0.1.0.dist-info/METADATA
yourlibname-0.1.0.dist-info/WHEEL
yourlibname-0.1.0.dist-info/entry_points.txt
yourlibname-0.1.0.dist-info/top_level.txt
yourlibname-0.1.0.dist-info/RECORD
