Metadata-Version: 2.4
Name: yourlibname
Version: 0.1.0
Summary: A minimal Python library template ready for PyPI
Author-email: YOUR NAME <you@example.com>
License: 📌 LICENSE (مثلاً MIT)
Project-URL: Homepage, https://example.com/yourlibname
Project-URL: Repository, https://example.com/yourlibname.git
Project-URL: Issues, https://example.com/yourlibname/issues
Classifier: Programming Language :: Python :: 3
Classifier: License :: OSI Approved :: MIT License
Classifier: Operating System :: OS Independent
Requires-Python: >=3.8
License-File: LICENSE
Dynamic: license-file
